oprfs/__init__.py
oprfs/oprfs.py
oprfs-2.0.0.dist-info/LICENSE
oprfs-2.0.0.dist-info/METADATA
oprfs-2.0.0.dist-info/WHEEL
oprfs-2.0.0.dist-info/top_level.txt
oprfs-2.0.0.dist-info/RECORD
